{
  "fraction": "Tyranids",
  "army": "Cult of the Rusted Claw",
  "version": "0.5.0",
  "release": "2020-05-03",
  "strategy": "Genestealer Cult armies have a Strategy Rating of 2.",
  "Initiative": "The Genestealer Swarm formation has an Initiative Rating of 1+. All other formations have an Initiative Rating of 2+, and are subject to the 'Broodmind' special rule.",
  "specialRules": [
    "Broodcoven",
    "Broodmind",
        "Brood Brothers",
        "Honour Guard",
        "Tunnelers"
  ],
  "usage": [],
  "units": [
    {
      "from": "GS2.json",
      "units": [
        "Brood Lord",
        "Genestealer Magus",
        "Genestealer Patriarch",
        "Genestealer Primus",
        "Hybrid Iconward",
        "Acolyte Praetorians",
        "Acolyte Hybrids",
        "Genestealers",
        "Aberrants",
        "Metamorph Hybrids",
        "Neophytes",
        "Neophyte Outriders",
        "Neophyte Fire Support",
        "Ridgerunner",
        "Land Transporter",
        "Technical",
        "Coven Limousine",
        "Goliath Truck",
        "Goliath Rockgrinder"
      ],
      "unitRules": [
      ]
    },
    {
      "from": "IG.json",
      "units": [
        "Chimera",
        "Basilisk",
        "Hellhound",
        "Hydra",
        "Leman Russ",
        "Sentinel"
      ],
      "unitRules": []
    },
    {
      "from": "ImperialNavy.json",
      "units": [
        "Thunderbolt Fighter"
      ],
      "unitRules": []
    }
  ],
  "sections": [
    {
      "name": "Acolyte Formations",
      "description": "One Broodcoven formation must be taken.",
      "formations": [
        {
          "name": "1 Broodcoven",
          "units": "One Genestealer Patriarch and six Acolyte Praetorians",
          "extraUnits": ["Cult Transports", "Technicals", "Acolytes"],
          "points": 275
        },
        {
          "name": "Acolyte Coven",
          "units": "Acolyte Praetorians with Hybrid Iconward, and seven Acolyte Hybrids",
          "extraUnits": ["Mineshaft Infiltrators", "Cult Transports", "Coven Leader", "Biomorphs", "Acolytes", "Technicals"],
          "points": 200
        }
      ]
    },
    {
      "name": "Purestrain Formations",
      "description": "Up to one Purestrain formation per Acolyte formation",
      "formations": [
        {
          "name": "Genestealer Swarm",
          "units": "One Brood Lord, six Genestealers",
          "extraUnits": [
            "Add up to three Genestealers: 25 points each"
          ],
          "points": 175
        }
      ]
  },
    {
      "name": "Neophyte Formations",
      "description": "Up to one Neophyte formation per Acolyte or Purestrain formation",
      "formations": [
          {
            "name": "Cult Sentinel Squadron",
            "units": "Four Sentinels",
            "extraUnits": [],
            "points": 100
          },
          {
            "name": "Outrider Squadron",
            "units": "One Hybrid Iconward, six Neophyte Outriders",
            "extraUnits": [
              "Ridgerunners"
            ],
            "points": 175
          },
        {
          "name": "Neophyte Platoon",
          "units": "One Hybrid Iconward, eight Neophytes",
          "extraUnits": [
            "Flak",
            "Fire Support"

          ],
          "points": 200
        },
        {
          "name": "Cult Artillery Battery",
          "units": "Three Basilisk",
          "extraUnits": [],
          "points": 250
        },
        {
          "name": "Mechanized Neophyte Platoon",
          "units": "One Hybrid Iconward, six Neophytes and three Chimeras",
          "extraUnits": [
            "Flak",
            "Hellhounds"
          ],
          "points": 275
      },

    {
      "name": "Cult Leman Russ Platoon",
      "units": "Six Leman Russ",
      "extraUnits": [],
      "points": 400
    },

    {
      "name": "Thunderbolts",
      "units": "Two Thunderbolts",
      "extraUnits": [],
      "points": 150
    }
      ]
    }
  ],
  "upgrades": {
    "title": "Upgrades",
    "description": "Each upgrade may be taken once per formation.",
    "items": [
        {
          "name": "Mineshaft Infiltrators",
          "description": "All units in the formation gains the 'Tunneling' special rule, but may have no other upgrades",
          "points": "Free"
        },
      {
        "name": "Acolyte Transports",
        "description": "Add Land Transporters, Coven Limousines, Goliath Trucks or Goliath Rockgrinders to the formation, up to the number required to transport all infantry units in the formation",
        "options": [
          {
            "description": "Land Transporter (Acolyte Coven only)",
            "points": "10 points each"
          },
          {
            "description": "Coven Limousine (Broodcoven only)",
            "points": "15 points each"
          },
          {
            "description": "Goliath Truck",
            "points": "25 points each"
          },
          {
            "description": "Goliath Rockgrinder",
            "points": "25 points each"
          }
        ]
      },
      {
        "name": "Coven Leader",
        "description": "Replace one Hybrid Iconward with a Genestealer Magus or Genestealer Primus",
        "points": "50 points"
      },
      {
        "name": "Fire Support",
        "description": "Add two Neophyte Fire Supports",
        "points": "75 points"
      },
      {
        "name": "Flak",
        "description": "Add one Hydra",
        "points": "50 points"
      },
      {
        "name": "Hellhounds",
        "description": "Add up to two Hellhounds",
        "points": "25 points each"
      },
      {
        "name": "Acolytes",
        "description": "Add up to four Acolyte Hybrids",
        "points": "15 points each"
      },
      {
        "name": "Biomorphs",
        "description": "Replace up to three Acolyte Hybrids with Aberrants and/or Metamorph Hybrids",
        "options": [
          {
            "description": "Aberrants",
            "points": "15 points each"
          },
          {
            "description": "Metamorph Hybrids",
            "points": "10 points each"
          }
        ]
      },
      {
        "name": "Riderunners",
        "description": "Add up to two Ridgerunners",
        "points": "20 points each"
      },
      {
        "name": "Technicals",
        "description": "Add up to two Technicals",
        "points": "25 points each"
      }
    ]
  }
}
